br_utils/__init__.py
br_utils/br_bank.py
br_utils/br_cities.py
br_utils/br_country.py
br_utils/br_states.py
br_utils/forms.py
br_utils/models.py
br_utils/utils.py
br_utils/validators.py
django_br_utils-0.4.dist-info/licenses/LICENSE
django_br_utils-0.4.dist-info/METADATA
django_br_utils-0.4.dist-info/WHEEL
django_br_utils-0.4.dist-info/top_level.txt
django_br_utils-0.4.dist-info/RECORD
